LICENSE
MANIFEST.in
README.rst
requirements.txt
setup.cfg
setup.py
ckanext/__init__.py
ckanext/mineduc_gt_theme/__init__.py
ckanext/mineduc_gt_theme/plugin.py
ckanext/mineduc_gt_theme/fanstatic/mineduc.css
ckanext/mineduc_gt_theme/public/img/background2.png
ckanext/mineduc_gt_theme/public/img/book.png
ckanext/mineduc_gt_theme/public/img/find.png
ckanext/mineduc_gt_theme/public/img/g2842.png
ckanext/mineduc_gt_theme/public/img/gobierno.png
ckanext/mineduc_gt_theme/public/img/hat.png
ckanext/mineduc_gt_theme/public/img/icon1.png
ckanext/mineduc_gt_theme/public/img/icon2.png
ckanext/mineduc_gt_theme/public/img/icon3.png
ckanext/mineduc_gt_theme/public/img/icon4.png
ckanext/mineduc_gt_theme/public/img/icon5.png
ckanext/mineduc_gt_theme/public/img/icon6.png
ckanext/mineduc_gt_theme/public/img/indicators.png
ckanext/mineduc_gt_theme/public/img/logo_mineduc.png
ckanext/mineduc_gt_theme/public/img/network.png
ckanext/mineduc_gt_theme/public/img/red.png
ckanext/mineduc_gt_theme/public/img/search.png
ckanext/mineduc_gt_theme/public/img/stats.png
ckanext/mineduc_gt_theme/templates/base.html
ckanext/mineduc_gt_theme/templates/footer.html
ckanext/mineduc_gt_theme/templates/header.html
ckanext/mineduc_gt_theme/templates/page.html
ckanext/mineduc_gt_theme/templates/home/index.html
ckanext/mineduc_gt_theme/templates/home/layout1.html
ckanext/mineduc_gt_theme/templates/home/snippets/promoted.html
ckanext/mineduc_gt_theme/tests/__init__.py
ckanext/mineduc_gt_theme/tests/test_plugin.py
ckanext_mineduc_gt_theme.egg-info/PKG-INFO
ckanext_mineduc_gt_theme.egg-info/SOURCES.txt
ckanext_mineduc_gt_theme.egg-info/dependency_links.txt
ckanext_mineduc_gt_theme.egg-info/entry_points.txt
ckanext_mineduc_gt_theme.egg-info/namespace_packages.txt
ckanext_mineduc_gt_theme.egg-info/top_level.txt