Metadata-Version: 1.1
Name: ckanext-mineduc-gt-theme
Version: 0.0.7
Summary: Portal de datos abiertos del Ministerio de Educación de Guatemala
Home-page: https://github.com/RedCiudadana/ckanext-mineduc_gt_theme
Author: Red ciudadana
Author-email: info@redciudadana.org
License: AGPL
Keywords: CKAN gt guatemala mineduc
Platform: UNKNOWN
Classifier: Development Status :: 4 - Beta
Classifier: License :: OSI Approved :: GNU Affero General Public License v3 or later (AGPLv3+)
Classifier: Programming Language :: Python :: 2.7
